fileop/__init__.py
fileop-0.0.2.dist-info/METADATA
fileop-0.0.2.dist-info/RECORD
fileop-0.0.2.dist-info/WHEEL
fileop-0.0.2.dist-info/top_level.txt
