Metadata-Version: 2.1
Name: fileop
Version: 0.0.2
Summary: All file operations without writing code for it
Home-page: https://github.com/saurabhlondhe/fileop
Author: Saurabh Londhe
Author-email: saurabhlondhe1111@gmail.com
License: UNKNOWN
Platform: UNKNOWN
Classifier: Programming Language :: Python :: 3.5
Classifier: Programming Language :: Python :: 3
Classifier: Programming Language :: Python :: 2
Classifier: License :: OSI Approved :: MIT License
Classifier: Operating System :: OS Independent
